rcsb/__init__.py
rcsb/exdb/__init__.py
rcsb/exdb/branch/BranchedEntityExtractor.py
rcsb/exdb/branch/GlycanProvider.py
rcsb/exdb/branch/GlycanUtils.py
rcsb/exdb/branch/__init__.py
rcsb/exdb/chemref/ChemRefEtlWorker.py
rcsb/exdb/chemref/ChemRefExtractor.py
rcsb/exdb/chemref/ChemRefMappingProvider.py
rcsb/exdb/chemref/PubChemDataCacheProvider.py
rcsb/exdb/chemref/PubChemEtlWrapper.py
rcsb/exdb/chemref/PubChemIndexCacheProvider.py
rcsb/exdb/chemref/__init__.py
rcsb/exdb/citation/CitationAdapter.py
rcsb/exdb/citation/CitationExtractor.py
rcsb/exdb/citation/CitationUtils.py
rcsb/exdb/citation/__init__.py
rcsb/exdb/cli/__init__.py
rcsb/exdb/entry/EntryInfoProvider.py
rcsb/exdb/entry/__init__.py
rcsb/exdb/examples-seq/EntityInstanceExtractor.py
rcsb/exdb/examples-seq/EntityPolymerExtractor.py
rcsb/exdb/examples-seq/EntityPolymerExtractorFullTests.py
rcsb/exdb/examples-seq/ReferenceSequenceAssignmentUpdater.py
rcsb/exdb/examples-seq/ReferenceSequenceUtils.py
rcsb/exdb/examples-seq/ReferenceSequenceUtilsTests.py
rcsb/exdb/examples-seq/exampleObjectExtractor.py
rcsb/exdb/examples-seq/fixtureEntityPolymerExtractor.py
rcsb/exdb/examples-seq/testEntityInstanceExtractor.py
rcsb/exdb/examples-seq/testEntityPolymerExtractor.py
rcsb/exdb/examples-seq/testReferenceSequenceAssignmentUpdater.py
rcsb/exdb/examples-seq/testReferenceSequenceUtils.py
rcsb/exdb/seq/AnnotationExtractor.py
rcsb/exdb/seq/LigandNeighborMappingExtractor.py
rcsb/exdb/seq/LigandNeighborMappingProvider.py
rcsb/exdb/seq/PolymerEntityExtractor.py
rcsb/exdb/seq/ReferenceSequenceAnnotationAdapter.py
rcsb/exdb/seq/ReferenceSequenceAnnotationProvider.py
rcsb/exdb/seq/ReferenceSequenceAssignmentAdapter.py
rcsb/exdb/seq/ReferenceSequenceAssignmentProvider.py
rcsb/exdb/seq/ReferenceSequenceCacheProvider.py
rcsb/exdb/seq/TaxonomyExtractor.py
rcsb/exdb/seq/UniProtCoreEtlWorker.py
rcsb/exdb/seq/UniProtExtractor.py
rcsb/exdb/seq/__init__.py
rcsb/exdb/tree/TreeNodeListWorker.py
rcsb/exdb/tree/__init__.py
rcsb_exdb-1.33.dist-info/METADATA
rcsb_exdb-1.33.dist-info/WHEEL
rcsb_exdb-1.33.dist-info/licenses/LICENSE
rcsb_exdb-1.33.dist-info/RECORD
