Metadata-Version: 2.4
Name: rcsb.exdb
Version: 1.33
Summary: RCSB Python ExDB data extraction and loading workflows
Project-URL: Homepage, https://github.com/rcsb/py-rcsb_exdb
Author-email: John Westbrook <john.westbrook@rcsb.org>
Maintainer-email: Dennis Piehl <dennis.piehl@rcsb.org>
License-Expression: Apache-2.0
License-File: LICENSE
Classifier: Development Status :: 5 - Production/Stable
Classifier: Intended Audience :: Developers
Classifier: Natural Language :: English
Classifier: Programming Language :: Python
Classifier: Programming Language :: Python :: 3
Classifier: Programming Language :: Python :: 3.12
Requires-Python: >=3.9
Requires-Dist: jsonschema>=2.6.0
Requires-Dist: numpy
Requires-Dist: openeye-toolkits>=2024.1.1
Requires-Dist: rcsb-db>=1.808
Requires-Dist: rcsb-utils-chem>=0.84
Requires-Dist: rcsb-utils-chemref>=0.91
Requires-Dist: rcsb-utils-config>=0.40
Requires-Dist: rcsb-utils-dictionary>=1.27
Requires-Dist: rcsb-utils-ec>=0.25
Requires-Dist: rcsb-utils-go>=0.18
Requires-Dist: rcsb-utils-io>=1.48
Requires-Dist: rcsb-utils-seq>=0.82
Requires-Dist: rcsb-utils-struct>=0.51
Requires-Dist: rcsb-utils-targets>=0.82
Requires-Dist: rcsb-utils-taxonomy>=0.43
Provides-Extra: tests
Requires-Dist: black>=21.5b1; extra == 'tests'
Requires-Dist: check-manifest; extra == 'tests'
Requires-Dist: coverage; extra == 'tests'
Requires-Dist: flake8; extra == 'tests'
Requires-Dist: pylint; extra == 'tests'
Requires-Dist: rcsb-utils-citation>=0.25; extra == 'tests'
Requires-Dist: tox; extra == 'tests'
